markets_insights/__init__.py
markets_insights/calculations/__init__.py
markets_insights/calculations/base.py
markets_insights/calculations/derivatives.py
markets_insights/calculations/equity.py
markets_insights/core/__init__.py
markets_insights/core/column_definition.py
markets_insights/core/core.py
markets_insights/core/environment.py
markets_insights/core/settings.py
markets_insights/dataprocess/__init__.py
markets_insights/dataprocess/data_processor.py
markets_insights/datareader/__init__.py
markets_insights/datareader/data_reader.py
markets_insights/trade_builders/__init__.py
markets_insights/trade_builders/derivatives.py
markets_insights/trade_builders/results.py
markets_insights-0.4.10.dist-info/METADATA
markets_insights-0.4.10.dist-info/WHEEL
markets_insights-0.4.10.dist-info/licenses/LICENSE.MD
markets_insights-0.4.10.dist-info/RECORD
