Metadata-Version: 2.3
Name: markets_insights
Version: 0.4.10
Summary: This package retrieves and handles financial market data from the National Stock Exchange (NSE) in India.
Project-URL: Homepage, https://github.com/nareshrohra/markets_insights/
Project-URL: Issues, https://github.com/nareshrohra/markets_insights/issues
Author-email: Naresh Rohra <naresh.rohra@hotmail.com>
License-File: LICENSE.MD
Classifier: Operating System :: OS Independent
Classifier: Programming Language :: Python :: 3
Requires-Python: >=3.8
